{
  "title": "مركز الإبداع - الأسئلة الموقفية في إدارة المشاريع الاحترافية",
  "description": "وصف الاختبار اللي يظهر في الصفحة الرئيسية",
  "time": 60,
  "pass": 75,
  "image": "https://imgs.search.brave.com/tC_EOIwXTBhInK1zNFFEGLa2mkidUN_4SpgjE9S01Io/rs:fit:860:0:0:0/g:ce/aHR0cHM6Ly9pbWcu/ZnJlZXBpay5jb20v/ZnJlZS1waG90by9h/aS1jbG91ZC1jb25j/ZXB0LXdpdGgtcm9i/b3QtYXJtc18yMy0y/MTQ5NzM5NzQ5Lmpw/Zz9zZW10PWFpc19o/eWJyaWQmdz03NDA",
  "test": [
    {
      "type": "multiple-choice",
      "text": "ما الاختيار الذي تكون اجابتك صحيحة اذا اخترته؟",
      "choices": [
        { "label": "أ", "text": "هذا الاختيار", "correct": false, "explanation": "هذا الاختيار هو الخطأ" },
        { "label": "ب", "text": "الاختيار اللي قبلي", "correct": false, "explanation": "هذا الاختيار هو الخطأ" },
        { "label": "ج", "text": "الاختيار اللي تحتي", "correct": true, "explanation": "هذا الاختيار هو الصحيح" },
        { "label": "د", "text": "جميع ما سبق", "correct": false, "explanation": "هذا الاختيار هو الخطأ" }
      ],
      "answer": 2
    },
    {
      "type": "multiple-choice",
      "text": "ما الاختيار الذي تكون اجابتك صحيحة اذا اخترته؟",
      "choices": [
        { "label": "أ", "text": "هذا الاختيار", "correct": false, "explanation": "هذا الاختيار هو الخطأ" },
        { "label": "ب", "text": "الاختيار اللي قبلي", "correct": false, "explanation": "هذا الاختيار هو الخطأ" },
        { "label": "ج", "text": "الاختيار اللي تحتي", "correct": true, "explanation": "هذا الاختيار هو الصحيح" },
        { "label": "د", "text": "جميع ما سبق", "correct": false, "explanation": "هذا الاختيار هو الخطأ" }
      ],
      "answer": 2
    },
    {
      "type": "multiple-choice",
      "text": "ما الاختيار الذي تكون اجابتك صحيحة اذا اخترته؟",
      "choices": [
        { "label": "أ", "text": "هذا الاختيار", "correct": false, "explanation": "هذا الاختيار هو الخطأ" },
        { "label": "ب", "text": "الاختيار اللي قبلي", "correct": false, "explanation": "هذا الاختيار هو الخطأ" },
        { "label": "ج", "text": "الاختيار اللي تحتي", "correct": true, "explanation": "هذا الاختيار هو الصحيح" },
        { "label": "د", "text": "جميع ما سبق", "correct": false, "explanation": "هذا الاختيار هو الخطأ" }
      ],
      "answer": 2
    },
    {
      "type": "multiple-choice",
      "text": "ما الاختيار الذي تكون اجابتك صحيحة اذا اخترته؟",
      "choices": [
        { "label": "أ", "text": "هذا الاختيار", "correct": false, "explanation": "هذا الاختيار هو الخطأ" },
        { "label": "ب", "text": "الاختيار اللي قبلي", "correct": false, "explanation": "هذا الاختيار هو الخطأ" },
        { "label": "ج", "text": "الاختيار اللي تحتي", "correct": true, "explanation": "هذا الاختيار هو الصحيح" },
        { "label": "د", "text": "جميع ما سبق", "correct": false, "explanation": "هذا الاختيار هو الخطأ" }
      ],
      "answer": 2
    },
    {
      "type": "multiple-choice",
      "text": "ما الاختيار الذي تكون اجابتك صحيحة اذا اخترته؟",
      "choices": [
        { "label": "أ", "text": "هذا الاختيار", "correct": false, "explanation": "هذا الاختيار هو الخطأ" },
        { "label": "ب", "text": "الاختيار اللي قبلي", "correct": false, "explanation": "هذا الاختيار هو الخطأ" },
        { "label": "ج", "text": "الاختيار اللي تحتي", "correct": true, "explanation": "هذا الاختيار هو الصحيح" },
        { "label": "د", "text": "جميع ما سبق", "correct": false, "explanation": "هذا الاختيار هو الخطأ" }
      ],
      "answer": 2
    },
    {
      "type": "multiple-choice",
      "text": "ما الاختيار الذي تكون اجابتك صحيحة اذا اخترته؟",
      "choices": [
        { "label": "أ", "text": "هذا الاختيار", "correct": false, "explanation": "هذا الاختيار هو الخطأ" },
        { "label": "ب", "text": "الاختيار اللي قبلي", "correct": false, "explanation": "هذا الاختيار هو الخطأ" },
        { "label": "ج", "text": "الاختيار اللي تحتي", "correct": true, "explanation": "هذا الاختيار هو الصحيح" },
        { "label": "د", "text": "جميع ما سبق", "correct": false, "explanation": "هذا الاختيار هو الخطأ" }
      ],
      "answer": 2
    },
    {
      "type": "multiple-choice",
      "text": "ما الاختيار الذي تكون اجابتك صحيحة اذا اخترته؟",
      "choices": [
        { "label": "أ", "text": "هذا الاختيار", "correct": false, "explanation": "هذا الاختيار هو الخطأ" },
        { "label": "ب", "text": "الاختيار اللي قبلي", "correct": false, "explanation": "هذا الاختيار هو الخطأ" },
        { "label": "ج", "text": "الاختيار اللي تحتي", "correct": true, "explanation": "هذا الاختيار هو الصحيح" },
        { "label": "د", "text": "جميع ما سبق", "correct": false, "explanation": "هذا الاختيار هو الخطأ" }
      ],
      "answer": 2
    },
    {
      "type": "multiple-choice",
      "text": "ما الاختيار الذي تكون اجابتك صحيحة اذا اخترته؟",
      "choices": [
        { "label": "أ", "text": "هذا الاختيار", "correct": false, "explanation": "هذا الاختيار هو الخطأ" },
        { "label": "ب", "text": "الاختيار اللي قبلي", "correct": false, "explanation": "هذا الاختيار هو الخطأ" },
        { "label": "ج", "text": "الاختيار اللي تحتي", "correct": true, "explanation": "هذا الاختيار هو الصحيح" },
        { "label": "د", "text": "جميع ما سبق", "correct": false, "explanation": "هذا الاختيار هو الخطأ" }
      ],
      "answer": 2
    },
    {
      "type": "multiple-choice",
      "text": "ما الاختيار الذي تكون اجابتك صحيحة اذا اخترته؟",
      "choices": [
        { "label": "أ", "text": "هذا الاختيار", "correct": false, "explanation": "هذا الاختيار هو الخطأ" },
        { "label": "ب", "text": "الاختيار اللي قبلي", "correct": false, "explanation": "هذا الاختيار هو الخطأ" },
        { "label": "ج", "text": "الاختيار اللي تحتي", "correct": true, "explanation": "هذا الاختيار هو الصحيح" },
        { "label": "د", "text": "جميع ما سبق", "correct": false, "explanation": "هذا الاختيار هو الخطأ" }
      ],
      "answer": 2
    }
  ]
}
